{
  "@context": "https://mif-spec.dev/schema/context.jsonld",
  "@type": "Concept",
  "@id": "urn:mif:concept:harness:citation-good-0001",
  "conceptType": "semantic",
  "title": "STORM multi-perspective fan-out outperforms single-pass RAG",
  "content": "Fan-out across multiple perspectives before synthesis improves organization (~25%) and coverage (~10%) over single-pass retrieval-augmented generation.",
  "created": "2026-06-19T12:00:00Z",
  "citations": [
    {
      "@type": "Citation",
      "citationType": "paper",
      "citationRole": "supports",
      "title": "Assisting in Writing Wikipedia-like Articles From Scratch with Large Language Models",
      "url": "https://arxiv.org/abs/2402.14207",
      "accessed": "2026-06-19"
    }
  ],
  "extensions": {
    "harness": {
      "dimension": "landscape",
      "verification": {
        "verdict": "survived",
        "verdict_basis": "Disconfirming search found no credible refutation of the reported gains."
      }
    }
  }
}
